{
    "theme_augmentations": {
        "color": "red",
        "font": "Arial",
        "size": "12px",
        "background": "white",
        "border": "1px solid black",
        "radius": "5px",
        "shadow": "2px 2px 2px 2px #888888"
    },  
    "component_names":
    [
        "Header",
        "Sidebar",
        "title",
       
     
        "AnalyticsConversionRates",
        "AnalyticsCurrentSubject",
        "AnalyticsNews",
        "AnalyticsCurrentVisits",
        "AnalyticsWebsiteVisits",
        "AnalyticsOrderTimeline",
        "AnalyticsTasks",
        "AnalyticsTrafficBySite",
        "AnalyticsWidgetSummary"
    ],
    "component_information":    
    {
        "Header": 
        {
            "count": 1,
            "location": "top of the page sticky",
            "description": "searchbar, language selection dropdown ,notification icon , contacts icon, setting icon with drawer functionality, user avatar"
        },
        "Sidebar": 
        {
            "count": 1,
            "location": "left of the page fixed",
            "description": "List of menu items with sub item "
        },
        "title": 
        {
            "count": 1,
            "location": "top left of main content",
            "description": "simple text"
         
        },
       
        "AnalyticsConversionRates": 
        {
            "count": 1,
            "location": "top left of main content taking 70% of full width ",
            "description": "horizontal graph for conversion rates"
        },
        "AnalyticsCurrentSubject": 
        {
            "count": 1,
            "location": "top right of main content taking 30% of full width ",
            "description": "analytics chart"
        },
        
        "AnalyticsNews": 
        {
            "count": 1,
            "location": "mid left 1st part  of main content taking 70% of full width ",
            "description": "Card with button and list"
        },
        "AnalyticsCurrentVisits": 
        {
            "count": 1,
            "location": "mid right  1st part of  main content taking 30% of full width ",
            "description": "Pie chart"
        },
       

        "AnalyticsWebsiteVisits":
        {
          "count": 1,
          "location": " its placed 2nd mid  left side of the ui layout",
          "description":"this is a AnalyticsWebsiteVisits representing a graph "
        },
        "AnalyticsOrderTimeline":
        {
          "count": 1,
          "location": " its placed 2nd right side of the ui layout",
          "description":"this is a card format and its shows Order Timeline "
        },
        "AnalyticsTasks":{
            "count": 1,
            "location": " its placed 3rd mid  left side of the ui layout",
            "description": "this card its representing a table inside the table their are a checkbox content its occuiped 70% of the width"
        },
        "AnalyticsTrafficBySite":{
            "count": 1,
            "location": " its placed 3rd mid  right side of the ui layout",
            "description": "this card its  representing social icons and followers its occuiped 30% of the width"
        },
        "AnalyticsWidgetSummary": 
        {
            "count": 4,
            "location":  "this section its placed in a bottom  left side",
            "description": "count for Weekly Sales, New Users, Item Orders, Bug Reports"
         
        },
        "functionality":
        {
            "sidebar_toggle": "a toggle feature that allows the sidebar to be hidden or shown"
        }
    }
}